[
  { "id": "es-00803", "en": "nervous", "ja": "緊張した、神経質な", "reason": "nervioso は形容詞で『神経質な/緊張した』。英訳 nerve(名詞『神経』=nervio)は品詞・意味とも誤り。" },
  { "id": "es-00808", "ja": "合計、全体", "reason": "『総数』は count のニュアンス。total は名詞で『合計/全体』が自然。" },
  { "id": "es-00812", "ja": "ナイフ、包丁", "reason": "『小刀』は短刀の意で不自然。cuchillo は一般的な『ナイフ/包丁』。" },
  { "id": "es-00818", "en": "broken", "ja": "壊れた", "reason": "roto は romper の過去分詞・形容詞『壊れた』。『broken thing or person』は冗長で不適切。" },
  { "id": "es-00826", "en": "shot", "ja": "射撃、発射", "reason": "tiro は名詞。和訳『投げる』は動詞形で品詞誤り。主要義は銃の『射撃/発射(一発)』。" },
  { "id": "es-00843", "en": "classes, lessons", "ja": "授業", "reason": "clases は clase の複数『授業/クラス』。英訳 tuition は米語で『授業料』とも取れ曖昧。" },
  { "id": "es-00893", "en": "direct", "ja": "直接の、生放送", "reason": "directo の主要義は形容詞『直接の』。live stream は en directo の一義に過ぎず主要義から外れる。" },
  { "id": "es-00894", "en": "central, headquarters", "ja": "中央の、本部", "reason": "central は形容詞『中央の』が主要義。headquarter は単数形も不自然。" },
  { "id": "es-00895", "en": "happy, content", "ja": "満足した、うれしい", "reason": "contento は形容詞『満足した/うれしい』。名詞 contentment は品詞誤り。" },
  { "id": "es-00901", "en": "open", "ja": "開いた", "reason": "abierta は abierto の女性形『開いた』。『act of opening(開くこと=apertura)』は誤り。" },
  { "id": "es-00905", "en": "natural", "ja": "自然の", "reason": "natural の主要義は『自然の』。native は副次的で主要義から外れる。" },
  { "id": "es-00956", "en": "property", "ja": "財産、所有権", "reason": "propiedad の主要義は『財産/所有権/特性』。propriety(礼儀)は空似言葉の誤訳。" },
  { "id": "es-00959", "en": "camp", "ja": "キャンプ、野営", "reason": "campamento は名詞『キャンプ地/野営』。camping は動名詞的で不自然。" },
  { "id": "es-00967", "en": "happened, occurred", "reason": "ocurrido は ocurrir の過去分詞『起きた/生じた』。unexpected(予期せぬ)は誤り。" },
  { "id": "es-00976", "en": "chest, breast", "ja": "胸", "reason": "pecho は日常語『胸』。thorax は解剖学用語で過度に専門的。" },
  { "id": "es-00984", "en": "handsome, good-looking", "ja": "ハンサムな、格好いい", "reason": "guapo は『ハンサムな/美しい』。arrowroot(葛=arrurruz)は完全な誤訳。" },
  { "id": "es-01011", "en": "whole, entire", "ja": "全体の、まるごと", "reason": "entero の主要義は形容詞『全体の/丸ごと』。whole number(整数)は数学の副次義。" },
  { "id": "es-01019", "en": "fat", "ja": "太った", "reason": "gordo は形容詞『太った』が主要義。fat man は限定的で不適切。" },
  { "id": "es-01039", "en": "female doctor", "ja": "女医", "reason": "doctora は doctor の女性形『女医』。doctor's wife(医者の妻)は古い誤訳。" },
  { "id": "es-01045", "en": "smooth", "ja": "滑らかな", "reason": "lisa は liso の女性形『滑らかな/平らな』。mullet(ボラ)は稀な魚名で主要義でない。" },
  { "id": "es-01083", "ja": "コース、講座", "reason": "curso の主要義は『講座/課程/コース』。『成り行き』は en curso の一義のみで狭い。" },
  { "id": "es-01092", "en": "speech", "ja": "演説、スピーチ", "reason": "discurso の主要義は『演説/スピーチ』。discourse は学術的副次義。" },
  { "id": "es-01093", "en": "short", "reason": "corta は corto の女性形『短い』(和訳 短い と一致)。英訳 cutting は不一致で誤り。" },
  { "id": "es-01117", "en": "empty", "ja": "空の、空虚", "reason": "vacío の主要義は形容詞『空の』。vacuum(真空)は限定的。" },
  { "id": "es-01123", "en": "famous", "ja": "有名な", "reason": "famoso は形容詞『有名な』が主要義。celebrity(名詞)とは品詞不一致。" },
  { "id": "es-01125", "en": "notes, grades", "ja": "メモ、成績", "reason": "notas は nota の複数『メモ/成績』。show-off は意味不明の誤訳。" },
  { "id": "es-01132", "en": "individual, subject", "ja": "人物、やつ", "reason": "sujeto は口語で『人物/やつ』、文法で『主語』。和訳『対象』は object の意で誤り。" },
  { "id": "es-01183", "en": "eaten", "ja": "食べた", "reason": "comido は comer の過去分詞『食べた』。『having had lunch(昼食を済ませた)』は狭く不自然。" },
  { "id": "es-01184", "en": "to throw, throw away", "ja": "投げる、捨てる", "reason": "tirar の主要義は『投げる/捨てる/引く』。『to drop intentionally』は狭すぎる。" },
  { "id": "es-01187", "en": "clean", "ja": "きれいな", "reason": "limpia は limpio の女性形『きれいな』。cleansing(名詞)は主要義でない。" },
  { "id": "es-01198", "en": "misfortune", "ja": "不幸、災難", "reason": "desgracia は『不幸/災難』。disgrace(恥辱)は空似言葉の誤訳、和訳『恥辱』も同様に誤り。" },

  { "id": "es-00861", "drop": true, "reason": "puto は男娼・侮蔑語の卑語。英訳も未翻訳のまま。学習に不適。" },
  { "id": "es-00884", "drop": true, "reason": "charles は固有名詞(人名)。hi-hat は打楽器の隠語で意味不定、一般語彙として不適。" },
  { "id": "es-00888", "drop": true, "reason": "leo は動詞 leer 一人称『(私は)読む』または星座 Leo。訳語も『leo』のまま未翻訳で意味不定。" },
  { "id": "es-00950", "drop": true, "reason": "quedo は動詞 quedar 一人称『残る/留まる』が実用上の主。形容詞『quiet』は文語的で誤導。" },
  { "id": "es-01016", "drop": true, "reason": "pongo は動詞 poner 一人称『(私は)置く』。orangutan(属名 Pongo)は誤導的で不適。" },
  { "id": "es-01033", "drop": true, "reason": "pete は俗語・地域語で意味不定。binky は意味不明の訳で学習に不適。" },
  { "id": "es-01087", "drop": true, "reason": "tenia はアクセント脱落した tenía(tener 未完了過去『持っていた』)の可能性大。tapeworm(条虫)は意図しない同綴語。" },
  { "id": "es-01126", "drop": true, "reason": "cabrón は主に侮蔑の卑語『クソ野郎』。字義『billy goat(雄山羊)』は実態を隠す不適切な訳。" }
]
